whittle/__init__.py
whittle/extract_subnetworks.py
whittle/eval/__init__.py
whittle/eval/utils.py
whittle/eval/whittle_llms.py
whittle/loss/__init__.py
whittle/loss/kd_loss.py
whittle/metrics/__init__.py
whittle/metrics/mag.py
whittle/metrics/parameters.py
whittle/models/__init__.py
whittle/models/gpt/__init__.py
whittle/models/gpt/extract.py
whittle/models/gpt/model.py
whittle/models/gpt/utils.py
whittle/models/gpt/blocks/__init__.py
whittle/models/gpt/blocks/causal_self_attention.py
whittle/models/gpt/blocks/mlp.py
whittle/models/gpt/blocks/transformer_block.py
whittle/modules/__init__.py
whittle/modules/embedding.py
whittle/modules/layernorm.py
whittle/modules/linear.py
whittle/modules/rmsnorm.py
whittle/sampling/__init__.py
whittle/sampling/random_sampler.py
whittle/search/__init__.py
whittle/search/ask_tell_scheduler.py
whittle/search/baselines.py
whittle/search/local_search.py
whittle/search/multi_objective.py
whittle/search/search.py
whittle/training_strategies/__init__.py
whittle/training_strategies/ats.py
whittle/training_strategies/base_strategy.py
whittle/training_strategies/random.py
whittle/training_strategies/random_linear.py
whittle/training_strategies/sandwich.py
whittle/training_strategies/standard.py
whittle/utils/__init__.py
whittle/utils/auto_search_config.py
whittle-0.1.3.dist-info/LICENSE
whittle-0.1.3.dist-info/METADATA
whittle-0.1.3.dist-info/WHEEL
whittle-0.1.3.dist-info/top_level.txt
whittle-0.1.3.dist-info/RECORD
