Metadata-Version: 2.1
Name: whittle
Version: 0.1.3
Summary: Two-stage neural architecture search for large language models
Author: Aaron Klein, Arber Zela, Rhea Sukthanker, Timur Carstensen
License: Apache License
Project-URL: homepage, https://github.com/whittle-org/whittle
Classifier: Intended Audience :: Science/Research
Classifier: Intended Audience :: Developers
Classifier: License :: OSI Approved :: Apache Software License
Classifier: Programming Language :: Python
Classifier: Topic :: Software Development
Classifier: Topic :: Scientific/Engineering
Classifier: Operating System :: POSIX
Classifier: Operating System :: Unix
Classifier: Operating System :: MacOS
Classifier: Programming Language :: Python :: 3
Classifier: Programming Language :: Python :: 3.9
Classifier: Programming Language :: Python :: 3.10
Classifier: Programming Language :: Python :: 3.11
Requires-Python: <3.12,>=3.9
License-File: LICENSE
Requires-Dist: pandas
Requires-Dist: matplotlib
Requires-Dist: typing-extensions
Requires-Dist: torch>=2
Requires-Dist: transformers>=4
Requires-Dist: litgpt[all]==0.4.5
Requires-Dist: syne-tune[moo]>=0.13
Requires-Dist: torchvision>=0.18
Provides-Extra: dev
Requires-Dist: build; extra == "dev"
Requires-Dist: pre-commit; extra == "dev"
Requires-Dist: pytest>=8; extra == "dev"
Requires-Dist: ruff; extra == "dev"
Requires-Dist: mypy; extra == "dev"
Requires-Dist: mike; extra == "dev"
Requires-Dist: mkdocs; extra == "dev"
Requires-Dist: mkdocs-material; extra == "dev"
Requires-Dist: mkdocs-autorefs; extra == "dev"
Requires-Dist: mkdocs-gen-files; extra == "dev"
Requires-Dist: mkdocs-literate-nav; extra == "dev"
Requires-Dist: mkdocstrings[python]; extra == "dev"
Requires-Dist: black; extra == "dev"
